mgn_kernel/__init__.py
mgn_kernel/common_ops.abi3.so
mgn_kernel/elementwise.py
mgn_kernel/moe.py
test_kernel_0ab602a9-0.1.4.dist-info/METADATA
test_kernel_0ab602a9-0.1.4.dist-info/WHEEL
test_kernel_0ab602a9-0.1.4.dist-info/licenses/LICENSE
test_kernel_0ab602a9-0.1.4.dist-info/RECORD
