Metadata-Version: 2.1
Name: test-kernel-0ab602a9
Version: 0.1.4
Summary: Custom CUDA Kernels for BatchGen Project
License:                                  Apache License
Classifier: Programming Language :: Python :: 3
Classifier: License :: OSI Approved :: Apache Software License
Classifier: Environment :: GPU :: NVIDIA CUDA
Requires-Python: >=3.9
